Workbook

Sheet Executive Dashboard
B2: PRISM TECHNOLOGIES INC. — CMO GTM EXECUTIVE DASHBOARD
B3: Institutional Go-To-Market Engine, Demand Gen Funnel Velocity & Channel Economics
B4: Institutional Cross-Venue Prediction Market Smart Order Router (Series Seed / Series A GTM Plan)
B6: Y1 SOURCED ARR | D6: Y1 PIPELINE CREATED | F6: PIPELINE COVERAGE | H6: BLENDED CAC | J6: MARKETING MAGIC NO.
B7: ='Funnel & Pipeline'!O25 | D7: ='Funnel & Pipeline'!O18 | F7: ='Funnel & Pipeline'!O29 | H7: ='Channel Economics'!J13 | J7: ='Marketing Budget'!O33
B10: ANNUAL GTM PERFORMANCE ROLLUP & SALES EFFICIENCY (5-YEAR OUTLOOK)
B11: Go-To-Market Metric | C11: Year 1 (Seed) | D11: Year 2 (Expansion) | E11: Year 3 (Scale) | F11: Year 4 (Institutional) | G11: Year 5 (Category King)
B12: Institutional MQLs Generated | C12: ='Funnel & Pipeline'!O15 | D12: =C12*2.8 | E12: =D12*2.5 | F12: =E12*1.9 | G12: =F12*1.6
B13: Sales Qualified Opportunities (SQLs) | C13: ='Funnel & Pipeline'!O17 | D13: =C13*2.8 | E13: =D13*2.5 | F13: =E13*1.9 | G13: =F13*1.6
B14: Technical Sandbox POCs Launched | C14: ='Funnel & Pipeline'!O21 | D14: =C14*2.6 | E14: =D14*2.4 | F14: =E14*1.8 | G14: =F14*1.5
B15: New Trading Desks Closed (Won) | C15: ='Funnel & Pipeline'!O23 | D15: =C15*3.0 | E15: =D15*2.5 | F15: =E15*1.8 | G15: =F15*1.5
B16: Cumulative Marketing-Sourced Desks | C16: =C15 | D16: =C16+D15 | E16: =D16+E15 | F16: =E16+F15 | G16: =F16+G15
B18: Marketing Sourced Pipeline ($M) | C18: ='Funnel & Pipeline'!O18/1000000 | D18: =C18*3.2 | E18: =D18*2.7 | F18: =E18*2.0 | G18: =F18*1.6
B19: Company Net ARR Quota Target ($M) | C19: 1.663 | D19: 7.128 | E19: 23.182 | F19: 48.361 | G19: 82.933
B20: Pipeline Coverage Ratio (vs Quota) | C20: =C18/C19 | D20: =D18/D19 | E20: =E18/E19 | F20: =F18/F19 | G20: =G18/G19
B21: Marketing Sourced Net ARR ($) | C21: ='Funnel & Pipeline'!O25 | D21: =C21*3.8 | E21: =D21*2.9 | F21: =E21*2.0 | G21: =F21*1.6
B22: Marketing Sourced ARR % of Total | C22: =C21/(C19*1000000) | D22: =D21/(D19*1000000) | E22: =E21/(E19*1000000) | F22: =F21/(F19*1000000) | G22: =G21/(G19*1000000)
B24: Total Marketing & GTM Spend ($) | C24: ='Marketing Budget'!O29 | D24: =C24*2.2 | E24: =D24*1.9 | F24: =E24*1.7 | G24: =F24*1.5
B25: Marketing Spend as % of Net ARR | C25: =C24/C21 | D25: =D24/D21 | E25: =E24/E21 | F25: =F24/F21 | G25: =G24/G21
B26: Blended Institutional CAC ($) | C26: =C24/C15 | D26: =D24/D15 | E26: =E24/E15 | F26: =F24/F15 | G26: =G24/G15
B27: Average Payback Period (Months) | C27: =(C26/(C21/C15))*12 | D27: =(D26/(D21/D15))*12 | E27: =(E26/(E21/E15))*12 | F27: =(F26/(F21/F15))*12 | G27: =(G26/(G21/G15))*12
B28: Marketing Magic Number (Efficiency) | C28: =C21/C24 | D28: =D21/D24 | E28: =E21/E24 | F28: =F21/F24 | G28: =G21/G24
B29: Institutional LTV / CAC Ratio | C29: ='Channel Economics'!L13 | D29: =C29*1.2 | E29: =D29*1.3 | F29: =E29*1.1 | G29: =F29*1.05

Sheet GTM Assumptions
B2: PRISM GO-TO-MARKET ARCHITECTURE — MASTER ASSUMPTIONS
B3: Institutional Target Accounts, Full-Funnel Conversion Rates, Deal Economics & Benchmarks
B5: 1. IDEAL CUSTOMER PROFILE (ICP) & TARGET ACCOUNT UNIVERSE
B6: Segment / Tier | C6: Target Accounts | D6: Unit | E6: Institutional Profile & Inclusions
B7: Tier 1: Global Market Makers & High-Volume Arbs | C7: 45 | D7: Desks | E7: Wintermute, Jump, GSR, FalconX, Flow Traders, QCP Capital
B8: Tier 2: Systematic Macro & Crypto Hedge Funds | C8: 250 | D8: Funds | E8: Brevan Howard, Galaxy, Pantera, Polychain, Point72 Crypto, Millennium
B9: Tier 3: Quantitative Prop Desks & Multi-Strat Boutiques | C9: 600 | D9: Desks | E9: Chicago/NYC prop trading firms executing statistical arbitrage
B10: Tier 4: Algorithmic Long-Tail Quant API Traders | C10: 2200 | D10: Traders | E10: Independent quant bots, Python systematic developers, sub-fund desks
B11: Total Global Institutional Target Market Universe | C11: 3095 | D11: Accounts | E11: Total accessible universe of institutions executing prediction flow
B13: 2. INSTITUTIONAL PIPELINE STAGE CONVERSION BENCHMARKS
B14: Pipeline Stage Transition | C14: Conversion Rate | D14: Unit | E14: Industry Benchmark / Institutional Validation Criteria
B15: Visitor / Viewer to Inbound Inquiry / SDK Clone | C15: 0.045 | D15: % | E15: 4.5% conversion of technical visitors exploring GitHub/docs
B16: Engaged Account to Marketing Qualified Account (MQL) | C16: 0.25 | D16: % | E16: 25.0% qualification (verified hedge fund / quant domain, >$10M AUM)
B17: MQL to Sales Qualified Opportunity (SQL) | C17: 0.4 | D17: % | E17: 40.0% transition (Head of Trading / CIO demo scheduled)
B18: SQL to Technical POC / Sandbox Trial Deployment | C18: 0.6 | D18: % | E18: 60.0% install API keys, run historical paper-arb simulator
B19: Technical POC to Compliance, Security & Legal Review | C19: 0.7 | D19: % | E19: 70.0% pass latency SLA (<0.5ms) & slippage proof (>200 bps saved)
B20: Compliance / Legal Review to Closed Won Master Contract | C20: 0.8 | D20: % | E20: 80.0% master service agreement (MSA) signed and live trading desk
B21: Full-Funnel Cumulative MQL to Closed-Won Win Rate | C21: 0.0672 | D21: % | E21: MQL to Closed Won compounding rate (0.25*0.40*0.60*0.70*0.80 = 6.72%)
B23: 3. CONTRACT VALUES (ACV) & SALES CYCLE DURATION
B24: Contract Metric | C24: Value | D24: Unit | E24: Strategic Context / Sourced Mix
B25: Tier 1 Core Quant API Annual ACV | C25: 30000 | D25: $ | E25: $2,500/mo base systematic API connection
B26: Tier 2 Institutional Desk (Flagship) Annual ACV | C26: 144000 | D26: $ | E26: $12,000/mo multi-seat terminal + Parity Radar
B27: Tier 3 Prime Direct (Enterprise) Annual ACV | C27: 420000 | D27: $ | E27: $35,000/mo dedicated VPC + custom TWAP algos
B28: Blended Average Annual Contract Value (ACV) | C28: 162000 | D28: $ | E28: Weighted average ACV across Tier 1, 2, and 3 contracts
B29: Average Institutional Sales Cycle Duration | C29: 45 | D29: Days | E29: Initial discovery call to live capital deployment
B30: Marketing Pipeline Quota Coverage Target | C30: 3.5 | D30: x | E30: Minimum pipeline generated required to guarantee ARR targets
B32: 4. MARKETING PROGRAM COSTS & CAMPAIGN BENCHMARKS
B33: Marketing Program / Asset | C33: Unit Cost | D33: Unit | E33: Scope of Deliverable / Execution Standard
B34: Proprietary Quant Alpha Research Whitepaper | C34: 12000 | D34: $ | E34: Deep microstructure data analysis + distribution to 5,000 CIOs
B35: Private Executive VIP Salon / Dinner (NYC/London/SG) | C35: 15000 | D35: $ | E35: Exclusive 12-person dinner for Heads of Trading & Macro CIOs
B36: Tier-1 Conference Major Presence (FIA Boca, Consensus) | C36: 45000 | D36: $ | E36: Executive meeting suite, stage keynote, VIP networking reception
B37: Technical Sales Engineering POC Enablement Cost | C37: 5000 | D37: $ | E37: Dedicated integration engineer hours per trial sandbox
B38: Target Inbound Cost per Qualified Lead (CPL) | C38: 850 | D38: $ | E38: Blended paid search, technical newsletters, and retargeting

Sheet Funnel & Pipeline
B2: PRISM 12-MONTH INSTITUTIONAL PIPELINE & FUNNEL WATERFALL
B3: Stage-by-Stage Account Progression from Inbound Awareness to Live Trading Desks
B5: Funnel Stage / Pipeline Metric | C5: Month 1 | D5: Month 2 | E5: Month 3 | F5: Month 4 | G5: Month 5 | H5: Month 6 | I5: Month 7 | J5: Month 8 | K5: Month 9 | L5: Month 10 | M5: Month 11 | N5: Month 12 | O5: Full Year 1
B6: TOP OF FUNNEL (AWARENESS & ENGAGEMENT)
B7: Unique Technical Web Visitors | C7: 1200 | D7: 1600 | E7: 2200 | F7: 3100 | G7: 4200 | H7: 5500 | I7: 6800 | J7: 8200 | K7: 9800 | L7: 11500 | M7: 13500 | N7: 16000 | O7: =SUM(C7:N7)
B8: Quant Research & Alpha Whitepaper Downloads | C8: 85 | D8: 120 | E8: 180 | F8: 260 | G8: 380 | H8: 510 | I8: 650 | J8: 810 | K8: 990 | L8: 1200 | M8: 1450 | N8: 1750 | O8: =SUM(C8:N8)
B9: GitHub Repo Stars & Python/Rust SDK Clones | C9: 45 | D9: 70 | E9: 110 | F9: 165 | G9: 240 | H9: 330 | I9: 430 | J9: 550 | K9: 680 | L9: 830 | M9: 1000 | N9: 1200 | O9: =SUM(C9:N9)
B10: Developer Sandbox API Registrations | C10: 18 | D10: 26 | E10: 38 | F10: 54 | G10: 76 | H10: 102 | I10: 132 | J10: 168 | K10: 208 | L10: 254 | M10: 306 | N10: 368 | O10: =SUM(C10:N10)
B11: Total Engaged Target Accounts | C11: =SUM(C8:C10) | D11: =SUM(D8:D10) | E11: =SUM(E8:E10) | F11: =SUM(F8:F10) | G11: =SUM(G8:G10) | H11: =SUM(H8:H10) | I11: =SUM(I8:I10) | J11: =SUM(J8:J10) | ... N11: =SUM(N8:N10) | O11: =SUM(C11:N11)
B13: MIDDLE OF FUNNEL (QUALIFICATION & DISCOVERY)
B14: Inbound Demo Requests & Form Submissions | C14: 12 | D14: 16 | E14: 24 | F14: 32 | G14: 42 | H14: 55 | I14: 68 | J14: 82 | K14: 98 | L14: 115 | M14: 135 | N14: 160 | O14: =SUM(C14:N14)
B15: Marketing Qualified Accounts (MQLs) | C15: =ROUND(C14*'GTM Assumptions'!C16, 0) | D15: =ROUND(D14*'GTM Assumptions'!C16, 0) | E15: =ROUND(E14*'GTM Assumptions'!C16, 0) | F15: =ROUND(F14*'GTM Assumptions'!C16, 0) | G15: =ROUND(G14*'GTM Assumptions'!C16, 0) | H15: =ROUND(H14*'GTM Assumptions'!C16, 0) | I15: =ROUND(I14*'GTM Assumptions'!C16, 0) | J15: =ROUND(J14*'GTM Assumptions'!C16, 0) | K15: =ROUND(K14*'GTM Assumptions'!C16, 0) | L15: =ROUND(L14*'GTM Assumptions'!C16, 0) | M15: =ROUND(M14*'GTM Assumptions'!C16, 0) | N15: =ROUND(N14*'GTM Assumptions'!C16, 0) | O15: =SUM(C15:N15)
B16: Discovery Calls Scheduled (Head of Trading) | C16: 6 | D16: 8 | E16: 12 | F16: 16 | G16: 21 | H16: 28 | I16: 34 | J16: 41 | K16: 49 | L16: 58 | M16: 68 | N16: 80 | O16: =SUM(C16:N16)
B17: Sales Qualified Opportunities (SQLs) | C17: =ROUND(C16*'GTM Assumptions'!C17, 0) | D17: =ROUND(D16*'GTM Assumptions'!C17, 0) | E17: =ROUND(E16*'GTM Assumptions'!C17, 0) | F17: =ROUND(F16*'GTM Assumptions'!C17, 0) | G17: =ROUND(G16*'GTM Assumptions'!C17, 0) | H17: =ROUND(H16*'GTM Assumptions'!C17, 0) | I17: =ROUND(I16*'GTM Assumptions'!C17, 0) | J17: =ROUND(J16*'GTM Assumptions'!C17, 0) | K17: =ROUND(K16*'GTM Assumptions'!C17, 0) | L17: =ROUND(L16*'GTM Assumptions'!C17, 0) | M17: =ROUND(M16*'GTM Assumptions'!C17, 0) | N17: =ROUND(N16*'GTM Assumptions'!C17, 0) | O17: =SUM(C17:N17)
B18: Pipeline Dollar Value Created ($) | C18: =C17*'GTM Assumptions'!C28 | D18: =D17*'GTM Assumptions'!C28 | E18: =E17*'GTM Assumptions'!C28 | F18: =F17*'GTM Assumptions'!C28 | G18: =G17*'GTM Assumptions'!C28 | H18: =H17*'GTM Assumptions'!C28 | I18: =I17*'GTM Assumptions'!C28 | J18: =J17*'GTM Assumptions'!C28 | K18: =K17*'GTM Assumptions'!C28 | L18: =L17*'GTM Assumptions'!C28 | M18: =M17*'GTM Assumptions'!C28 | N18: =N17*'GTM Assumptions'!C28 | O18: =SUM(C18:N18)
B20: LATE FUNNEL (EVALUATION & CLOSING)
B21: Technical Sandbox POCs Launched | C21: =ROUND(C17*'GTM Assumptions'!C18, 0) | D21: =ROUND(D17*'GTM Assumptions'!C18, 0) | E21: =ROUND(E17*'GTM Assumptions'!C18, 0) | F21: =ROUND(F17*'GTM Assumptions'!C18, 0) | G21: =ROUND(G17*'GTM Assumptions'!C18, 0) | H21: =ROUND(H17*'GTM Assumptions'!C18, 0) | I21: =ROUND(I17*'GTM Assumptions'!C18, 0) | J21: =ROUND(J17*'GTM Assumptions'!C18, 0) | K21: =ROUND(K17*'GTM Assumptions'!C18, 0) | L21: =ROUND(L17*'GTM Assumptions'!C18, 0) | M21: =ROUND(M17*'GTM Assumptions'!C18, 0) | N21: =ROUND(N17*'GTM Assumptions'!C18, 0) | O21: =SUM(C21:N21)
B22: Compliance & Security Due Diligence Reviews | C22: =ROUND(C21*'GTM Assumptions'!C19, 0) | D22: =ROUND(D21*'GTM Assumptions'!C19, 0) | E22: =ROUND(E21*'GTM Assumptions'!C19, 0) | F22: =ROUND(F21*'GTM Assumptions'!C19, 0) | G22: =ROUND(G21*'GTM Assumptions'!C19, 0) | H22: =ROUND(H21*'GTM Assumptions'!C19, 0) | I22: =ROUND(I21*'GTM Assumptions'!C19, 0) | J22: =ROUND(J21*'GTM Assumptions'!C19, 0) | K22: =ROUND(K21*'GTM Assumptions'!C19, 0) | L22: =ROUND(L21*'GTM Assumptions'!C19, 0) | M22: =ROUND(M21*'GTM Assumptions'!C19, 0) | N22: =ROUND(N21*'GTM Assumptions'!C19, 0) | O22: =SUM(C22:N22)
B23: New Closed Won Institutional Desks | C23: 1 | D23: 0 | E23: 1 | F23: 1 | G23: 1 | H23: 1 | I23: 1 | J23: 1 | K23: 1 | L23: 2 | M23: 1 | N23: 1 | O23: =SUM(C23:N23)
B24: Cumulative Live Trading Desks | C24: =C23 | D24: =C24+D23 | E24: =D24+E23 | F24: =E24+F23 | G24: =F24+G23 | H24: =G24+H23 | I24: =H24+I23 | J24: =I24+J23 | K24: =J24+K23 | ... N24: =M24+N23 | O24: =N24
B25: Monthly Sourced New ARR ($) | C25: =C23*'GTM Assumptions'!C28 | D25: =D23*'GTM Assumptions'!C28 | E25: =E23*'GTM Assumptions'!C28 | F25: =F23*'GTM Assumptions'!C28 | G25: =G23*'GTM Assumptions'!C28 | H25: =H23*'GTM Assumptions'!C28 | I25: =I23*'GTM Assumptions'!C28 | J25: =J23*'GTM Assumptions'!C28 | K25: =K23*'GTM Assumptions'!C28 | L25: =L23*'GTM Assumptions'!C28 | M25: =M23*'GTM Assumptions'!C28 | N25: =N23*'GTM Assumptions'!C28 | O25: =SUM(C25:N25)
B26: Cumulative Sourced ARR ($) | C26: =C25 | D26: =C26+D25 | E26: =D26+E25 | F26: =E26+F25 | G26: =F26+G25 | H26: =G26+H25 | I26: =H26+I25 | J26: =I26+J25 | K26: =J26+K25 | ... N26: =M26+N25 | O26: =N26
B28: PIPELINE VELOCITY & COVERAGE
B29: Monthly Pipeline Coverage Ratio (vs Target) | C29: =C18/(C25+1) | D29: =D18/(D25+1) | E29: =E18/(E25+1) | F29: =F18/(F25+1) | G29: =G18/(G25+1) | H29: =H18/(H25+1) | I29: =I18/(I25+1) | J29: =J18/(J25+1) | ... N29: =N18/(N25+1) | O29: =O18/O25
B30: Monthly Pipeline Velocity Index ($/Day) | C30: =(C17*'GTM Assumptions'!C21*'GTM Assumptions'!C28)/'GTM Assumptions'!C29 | D30: =(D17*'GTM Assumptions'!C21*'GTM Assumptions'!C28)/'GTM Assumptions'!C29 | E30: =(E17*'GTM Assumptions'!C21*'GTM Assumptions'!C28)/'GTM Assumptions'!C29 | F30: =(F17*'GTM Assumptions'!C21*'GTM Assumptions'!C28)/'GTM Assumptions'!C29 | G30: =(G17*'GTM Assumptions'!C21*'GTM Assumptions'!C28)/'GTM Assumptions'!C29 | H30: =(H17*'GTM Assumptions'!C21*'GTM Assumptions'!C28)/'GTM Assumptions'!C29 | I30: =(I17*'GTM Assumptions'!C21*'GTM Assumptions'!C28)/'GTM Assumptions'!C29 | J30: =(J17*'GTM Assumptions'!C21*'GTM Assumptions'!C28)/'GTM Assumptions'!C29 | K30: =(K17*'GTM Assumptions'!C21*'GTM Assumptions'!C28)/'GTM Assumptions'!C29 | L30: =(L17*'GTM Assumptions'!C21*'GTM Assumptions'!C28)/'GTM Assumptions'!C29 | M30: =(M17*'GTM Assumptions'!C21*'GTM Assumptions'!C28)/'GTM Assumptions'!C29 | N30: =(N17*'GTM Assumptions'!C21*'GTM Assumptions'!C28)/'GTM Assumptions'!C29 | O30: =AVERAGE(C30:N30)

Sheet Channel Economics
B2: PRISM INSTITUTIONAL MARKETING CHANNELS & UNIT ECONOMICS
B3: Comparative Analysis of CAC, LTV/CAC, Payback & Sourced Revenue by Acquisition Channel
B5: ACQUISITION CHANNEL PERFORMANCE MATRIX (YEAR 1 ACTUAL / BUDGET)
B6: Marketing Acquisition Channel | C6: Target Persona / Playbook | D6: Annual Budget | E6: MQLs | F6: SQLs | G6: POC Trials | H6: Closed Won | I6: Sourced ARR | J6: Channel CAC | K6: Channel LTV | L6: LTV / CAC | M6: Payback (Mo)
B7: Account-Based Marketing (ABM) & Outbound | C7: Top 50 MM & Macro Funds (Wintermute, Jump) | D7: 85000 | E7: 32 | F7: 14 | G7: 8 | H7: 4 | I7: =H7*'GTM Assumptions'!C28 | J7: =D7/H7 | K7: 3384000 | L7: =K7/J7 | M7: =(J7/(I7/H7))*12
B8: Quantitative Research & Alpha Whitepapers | C8: Systematic PMs, Quant Researchers | D8: 55000 | E8: 48 | F8: 18 | G8: 10 | H8: 3 | I8: =H8*'GTM Assumptions'!C28 | J8: =D8/H8 | K8: 3384000 | L8: =K8/J8 | M8: =(J8/(I8/H8))*12
B9: Developer Relations & Open Source SDKs | C9: Quant Algo Developers, Python/Rust Bots | D9: 65000 | E9: 55 | F9: 16 | G9: 9 | H9: 2 | I9: =H9*'GTM Assumptions'!C28 | J9: =D9/H9 | K9: 345000 | L9: =K9/J9 | M9: =(J9/(I9/H9))*12
B10: Industry Conferences & Executive VIP Salons | C10: Heads of Trading, CIOs, Managing Partners | D10: 115000 | E10: 24 | F10: 12 | G10: 7 | H10: 2 | I10: =H10*'GTM Assumptions'!C28 | J10: =D10/H10 | K10: 3384000 | L10: =K10/J10 | M10: =(J10/(I10/H10))*12
B11: Exchange & Venue Ecosystem Co-Marketing | C11: Polymarket & Kalshi Institutional Flow | D11: 40000 | E11: 35 | F11: 15 | G11: 8 | H11: 1 | I11: =H11*'GTM Assumptions'!C28 | J11: =D11/H11 | K11: 20160000 | L11: =K11/J11 | M11: =(J11/(I11/H11))*12
B13: TOTAL / BLENDED PORTFOLIO AVERAGE | D13: =SUM(D7:D11) | E13: =SUM(E7:E11) | F13: =SUM(F7:F11) | G13: =SUM(G7:G11) | H13: =SUM(H7:H11) | I13: =SUM(I7:I11) | J13: =D13/H13 | K13: =AVERAGE(K7:K11) | L13: =K13/J13 | M13: =(J13/(I13/H13))*12

Sheet Marketing Budget
B2: PRISM 12-MONTH MARKETING BUDGET & OPEX ALLOCATION
B3: Headcount, Program Spend, MarTech Infrastructure, and Capital Efficiency Monitoring
B5: Budget Category / Line Item | C5: Month 1 | D5: Month 2 | E5: Month 3 | F5: Month 4 | G5: Month 5 | H5: Month 6 | I5: Month 7 | J5: Month 8 | K5: Month 9 | L5: Month 10 | M5: Month 11 | N5: Month 12 | O5: Full Year 1
B6: 1. MARKETING PERSONNEL & HEADCOUNT
B7: VP Marketing / Chief Marketing Officer | C7: 18300 | D7: 18300 | E7: 18300 | F7: 18300 | G7: 18300 | H7: 18300 | I7: 18300 | J7: 18300 | K7: 18300 | L7: 18300 | M7: 18300 | N7: 18300 | O7: =SUM(C7:N7)
B8: Quantitative Research & Content Lead | C8: 0 | D8: 15250 | E8: 15250 | F8: 15250 | G8: 15250 | H8: 15250 | I8: 15250 | J8: 15250 | K8: 15250 | L8: 15250 | M8: 15250 | N8: 15250 | O8: =SUM(C8:N8)
B9: Developer Relations & Quant Evangelist | C9: 0 | D9: 0 | E9: 16267 | F9: 16267 | G9: 16267 | H9: 16267 | I9: 16267 | J9: 16267 | K9: 16267 | L9: 16267 | M9: 16267 | N9: 16267 | O9: =SUM(C9:N9)
B10: Events & Growth Operations Specialist | C10: 0 | D10: 0 | E10: 0 | F10: 11183 | G10: 11183 | H10: 11183 | I10: 11183 | J10: 11183 | K10: 11183 | L10: 11183 | M10: 11183 | N10: 11183 | O10: =SUM(C10:N10)
B11: Total Marketing Headcount Cost | C11: =SUM(C7:C10) | D11: =SUM(D7:D10) | E11: =SUM(E7:E10) | F11: =SUM(F7:F10) | G11: =SUM(G7:G10) | H11: =SUM(H7:H10) | I11: =SUM(I7:I10) | J11: =SUM(J7:J10) | ... N11: =SUM(N7:N10) | O11: =SUM(C11:N11)
B13: 2. MARKETING CAMPAIGNS & PROGRAM SPEND
B14: Proprietary Quant Alpha Research Reports | C14: 0 | D14: 12000 | E14: 0 | F14: 12000 | G14: 0 | H14: 12000 | I14: 0 | J14: 12000 | K14: 0 | L14: 12000 | M14: 0 | N14: 12000 | O14: =SUM(C14:N14)
B15: Sponsored Technical Media & Retargeting | C15: 3500 | D15: 4500 | E15: 5000 | F15: 5000 | G15: 5500 | H15: 5500 | I15: 6000 | J15: 6000 | K15: 6500 | L15: 6500 | M15: 7000 | N15: 7000 | O15: =SUM(C15:N15)
B16: Major Conferences & Executive VIP Salons | C16: 0 | D16: 15000 | E16: 45000 | F16: 0 | G16: 15000 | H16: 45000 | I16: 0 | J16: 15000 | K16: 0 | L16: 30000 | M16: 15000 | N16: 0 | O16: =SUM(C16:N16)
B17: DevRel Hackathons, Bug Bounties & Grants | C17: 0 | D17: 0 | E17: 10000 | F17: 0 | G17: 0 | H17: 15000 | I17: 0 | J17: 0 | K17: 15000 | L17: 0 | M17: 0 | N17: 10000 | O17: =SUM(C17:N17)
B18: Institutional PR & Communications Agency | C18: 6000 | D18: 6000 | E18: 6000 | F18: 6000 | G18: 6000 | H18: 6000 | I18: 6000 | J18: 6000 | K18: 6000 | L18: 6000 | M18: 6000 | N18: 6000 | O18: =SUM(C18:N18)
B19: Design, Brand Identity & Motion Assets | C19: 5000 | D19: 2500 | E19: 2500 | F19: 2500 | G19: 2500 | H19: 2500 | I19: 2500 | J19: 2500 | K19: 2500 | L19: 2500 | M19: 2500 | N19: 2500 | O19: =SUM(C19:N19)
B20: Total Marketing Program Spend | C20: =SUM(C14:C19) | D20: =SUM(D14:D19) | E20: =SUM(E14:E19) | F20: =SUM(F14:F19) | G20: =SUM(G14:G19) | H20: =SUM(H14:H19) | I20: =SUM(I14:I19) | J20: =SUM(J14:J19) | ... N20: =SUM(N14:N19) | O20: =SUM(C20:N20)
B22: 3. MARKETING TECHNOLOGY & SOFTWARE (MARTECH)
B23: HubSpot / Salesforce Enterprise CRM | C23: 2000 | D23: 2000 | E23: 2000 | F23: 2000 | G23: 2000 | H23: 2000 | I23: 2000 | J23: 2000 | K23: 2000 | L23: 2000 | M23: 2000 | N23: 2000 | O23: =SUM(C23:N23)
B24: 6sense / Demandbase ABM Intent Data | C24: 3000 | D24: 3000 | E24: 3000 | F24: 3000 | G24: 3000 | H24: 3000 | I24: 3000 | J24: 3000 | K24: 3000 | L24: 3000 | M24: 3000 | N24: 3000 | O24: =SUM(C24:N24)
B25: Apollo / ZoomInfo Verified Contacts | C25: 1500 | D25: 1500 | E25: 1500 | F25: 1500 | G25: 1500 | H25: 1500 | I25: 1500 | J25: 1500 | K25: 1500 | L25: 1500 | M25: 1500 | N25: 1500 | O25: =SUM(C25:N25)
B26: Webflow, Segment, Hosting & Analytics | C26: 800 | D26: 800 | E26: 800 | F26: 800 | G26: 800 | H26: 800 | I26: 800 | J26: 800 | K26: 800 | L26: 800 | M26: 800 | N26: 800 | O26: =SUM(C26:N26)
B27: Total MarTech & Tooling Spend | C27: =SUM(C23:C26) | D27: =SUM(D23:D26) | E27: =SUM(E23:E26) | F27: =SUM(F23:F26) | G27: =SUM(G23:G26) | H27: =SUM(H23:H26) | I27: =SUM(I23:I26) | J27: =SUM(J23:J26) | ... N27: =SUM(N23:N26) | O27: =SUM(C27:N27)
B29: TOTAL MARKETING & GTM OUTFLOW | C29: =C11+C20+C27 | D29: =D11+D20+D27 | E29: =E11+E20+E27 | F29: =F11+F20+F27 | G29: =G11+G20+G27 | H29: =H11+H20+H27 | I29: =I11+I20+I27 | J29: =J11+J20+J27 | ... N29: =N11+N20+N27 | O29: =SUM(C29:N29)
B30: Cumulative Marketing Spend ($) | C30: =C29 | D30: =C30+D29 | E30: =D30+E29 | F30: =E30+F29 | G30: =F30+G29 | H30: =G30+H29 | I30: =H30+I29 | J30: =I30+J29 | K30: =J30+K29 | ... N30: =M30+N29 | O30: =N30
B31: Monthly Sourced ARR ($) | C31: ='Funnel & Pipeline'!C25 | D31: ='Funnel & Pipeline'!D25 | E31: ='Funnel & Pipeline'!E25 | F31: ='Funnel & Pipeline'!F25 | G31: ='Funnel & Pipeline'!G25 | H31: ='Funnel & Pipeline'!H25 | I31: ='Funnel & Pipeline'!I25 | J31: ='Funnel & Pipeline'!J25 | ... O31: ='Funnel & Pipeline'!O25
B32: Cumulative Sourced ARR ($) | C32: ='Funnel & Pipeline'!C26 | D32: ='Funnel & Pipeline'!D26 | E32: ='Funnel & Pipeline'!E26 | F32: ='Funnel & Pipeline'!F26 | G32: ='Funnel & Pipeline'!G26 | H32: ='Funnel & Pipeline'!H26 | I32: ='Funnel & Pipeline'!I26 | J32: ='Funnel & Pipeline'!J26 | ... N32: ='Funnel & Pipeline'!N26 | O32: =N32
B33: Marketing Efficiency (Sourced ARR / Spend) | C33: =C32/C30 | D33: =D32/D30 | E33: =E32/E30 | F33: =F32/F30 | G33: =G32/G30 | H33: =H32/H30 | I33: =I32/I30 | J33: =J32/J30 | ... N33: =N32/N30 | O33: =O31/O29

Sheet GTM Launch Calendar
B2: PRISM 12-MONTH GO-TO-MARKET EXECUTION ROADMAP
B3: Chronological Milestones, Campaign Activations, Research Launches, and Field Marketing
B5: ANNUAL GTM EXECUTION CALENDAR & PRODUCT MARKETING ROADMAP
B6: Month | C6: Quarter | D6: Campaign / Milestone Initiative | E6: Category | F6: Target Audience | G6: Key Deliverable / Asset | H6: Primary KPI Target
B7: Month 1 | C7: Q1 | D7: Brand & Institutional Website Relaunch | E7: Brand & Product | F7: Global Macro & Quant Funds | G7: Interactive Parity Radar demo & Docs portal | H7: 1,200 unique visitors, 18 API sandboxes
B8: Month 2 | C8: Q1 | D8: Research Paper: 'The Cross-Venue Liquidity Gap' | E8: Quant Research | F8: Systematic Crypto & Prop Desks | G8: 18-page microstructure whitepaper + dataset | H8: 500 downloads, 15 inbound MQLs
B9: Month 3 | C9: Q1 | D9: Consensus & FIA Boca Private Dinner Salon | E9: Field Marketing | F9: Top 20 Crypto Market Makers & Arbs | G9: 12-person private VIP dinner in Delray Beach | H9: 4 Technical POCs launched
B10: Month 4 | C10: Q2 | D10: PRISM Python & Rust SDK v1.0 Launch | E10: DevRel & Product | F10: Systematic Algo Developers | G10: Open-source GitHub repo, FIX drop-copy guide | H10: 150 stars, 50 git clones, 8 MQLs
B11: Month 5 | C11: Q2 | D11: Research Paper: 'Oracle Latency & Resolution Risk' | E11: Quant Research | F11: Event-Driven & Macro PMs | G11: Empirical study on UMA vs Pyth resolution lag | H11: 750 downloads, 20 inbound MQLs
B12: Month 6 | C12: Q2 | D12: Tier 2 Institutional Desk Flagship Campaign | E12: ABM Outbound | F12: Mid-Tier Multi-Strat Hedge Funds | G12: Bespoke slippage audit reports per fund | H12: 6 SQLs, 2 live desks signed
B13: Month 7 | C13: Q3 | D13: Polymarket & Kalshi Co-Marketing Webinar | E13: Ecosystem | F13: Institutional Prediction Market Participants | G13: Joint technical webinar on order routing efficiency | H13: 800 registrants, 35 MQLs
B14: Month 8 | C14: Q3 | D14: London Quant Executive Salon (Mayfair) | E14: Field Marketing | F14: UK & European Macro Hedge Funds | G14: Private salon dinner during London Blockchain Week | H14: 3 Technical POCs launched
B15: Month 9 | C15: Q3 | D15: PRISM Quant Trading Hackathon ($50k Prizes) | E15: DevRel & Community | F15: Algorithmic Quants & Student Trading Clubs | G15: Live sandbox paper-arb competition | H15: 250 participating quants, 5 Tier 1 API clients
B16: Month 10 | C16: Q4 | D16: Annual 'State of Prediction Markets' Report | E16: Flagship Content | F16: Institutional Investors & Industry Media | G16: Comprehensive 35-page annual market review | H16: 2,500 downloads, Bloomberg/Coindesk press
B17: Month 11 | C17: Q4 | D17: Secaucus NY4 Co-Location Expansion Launch | E17: Enterprise Product | F17: Tier 1 High-Frequency Market Makers | G17: Direct 10Gbps cross-connect latency benchmark | H17: 2 Prime Direct / Co-Lo contracts signed
B18: Month 12 | C18: Q4 | D18: Annual GTM Retrospective & 2027 Scale Kickoff | E18: Strategy & Ops | F18: Internal Executive Team & Board | G18: Audited cohort CAC, LTV, and ARR attribution deck | H18: Full Year $1.94M ARR milestone locked
